<dataset><name>Training faces</name><comment>This is Rob's XML data for use with DLib shape trainer.</comment><images><image file="images/robshapes2_frame118.jpg"><box top="100" left="100" width="880" height="1000"><part name="00" x="223" y="495" /><part name="01" x="226" y="576" /><part name="02" x="241" y="658" /><part name="03" x="254" y="738" /><part name="04" x="289" y="818" /><part name="05" x="322" y="891" /><part name="06" x="374" y="961" /><part name="07" x="452" y="1023" /><part name="08" x="535" y="1042" /><part name="09" x="626" y="1019" /><part name="10" x="675" y="965" /><part name="11" x="719" y="893" /><part name="12" x="765" y="822" /><part name="13" x="787" y="743" /><part name="14" x="801" y="656" /><part name="15" x="806" y="575" /><part name="16" x="807" y="484" /><part name="17" x="255" y="474" /><part name="18" x="287" y="433" /><part name="19" x="330" y="432" /><part name="20" x="392" y="433" /><part name="21" x="456" y="448" /><part name="22" x="561" y="456" /><part name="23" x="621" y="437" /><part name="24" x="681" y="428" /><part name="25" x="737" y="439" /><part name="26" x="778" y="476" /><part name="27" x="518" y="529" /><part name="28" x="523" y="599" /><part name="29" x="527" y="668" /><part name="30" x="528" y="741" /><part name="31" x="442" y="745" /><part name="32" x="482" y="760" /><part name="33" x="528" y="779" /><part name="34" x="569" y="761" /><part name="35" x="606" y="742" /><part name="36" x="324" y="523" /><part name="37" x="363" y="498" /><part name="38" x="413" y="498" /><part name="39" x="448" y="520" /><part name="40" x="415" y="550" /><part name="41" x="366" y="549" /><part name="42" x="597" y="522" /><part name="43" x="639" y="498" /><part name="44" x="680" y="498" /><part name="45" x="716" y="518" /><part name="46" x="683" y="542" /><part name="47" x="640" y="544" /><part name="48" x="410" y="845" /><part name="49" x="455" y="836" /><part name="50" x="494" y="836" /><part name="51" x="527" y="844" /><part name="52" x="556" y="835" /><part name="53" x="598" y="839" /><part name="54" x="644" y="851" /><part name="55" x="598" y="889" /><part name="56" x="558" y="902" /><part name="57" x="523" y="910" /><part name="58" x="491" y="902" /><part name="59" x="448" y="887" /><part name="60" x="419" y="848" /><part name="61" x="482" y="863" /><part name="62" x="525" y="869" /><part name="63" x="571" y="861" /><part name="64" x="635" y="850" /><part name="65" x="571" y="861" /><part name="66" x="525" y="869" /><part name="67" x="482" y="863" /></box></image><image file="images/robshapes2_frame178.jpg"><box top="100" left="100" width="880" height="1000"><part name="00" x="223" y="495" /><part name="01" x="225" y="582" /><part name="02" x="240" y="673" /><part name="03" x="267" y="754" /><part name="04" x="312" y="837" /><part name="05" x="338" y="926" /><part name="06" x="378" y="1006" /><part name="07" x="451" y="1083" /><part name="08" x="534" y="1110" /><part name="09" x="626" y="1077" /><part name="10" x="675" y="1015" /><part name="11" x="719" y="934" /><part name="12" x="758" y="852" /><part name="13" x="781" y="764" /><part name="14" x="801" y="671" /><part name="15" x="806" y="582" /><part name="16" x="808" y="484" /><part name="17" x="255" y="474" /><part name="18" x="287" y="433" /><part name="19" x="330" y="432" /><part name="20" x="392" y="433" /><part name="21" x="456" y="448" /><part name="22" x="562" y="456" /><part name="23" x="622" y="437" /><part name="24" x="682" y="428" /><part name="25" x="738" y="439" /><part name="26" x="779" y="476" /><part name="27" x="518" y="529" /><part name="28" x="523" y="599" /><part name="29" x="527" y="669" /><part name="30" x="528" y="742" /><part name="31" x="442" y="746" /><part name="32" x="482" y="761" /><part name="33" x="528" y="780" /><part name="34" x="570" y="762" /><part name="35" x="607" y="743" /><part name="36" x="324" y="523" /><part name="37" x="363" y="498" /><part name="38" x="413" y="498" /><part name="39" x="448" y="520" /><part name="40" x="415" y="550" /><part name="41" x="366" y="549" /><part name="42" x="598" y="522" /><part name="43" x="634" y="497" /><part name="44" x="681" y="498" /><part name="45" x="717" y="518" /><part name="46" x="684" y="542" /><part name="47" x="641" y="544" /><part name="48" x="424" y="893" /><part name="49" x="465" y="854" /><part name="50" x="498" y="846" /><part name="51" x="527" y="862" /><part name="52" x="556" y="842" /><part name="53" x="592" y="851" /><part name="54" x="631" y="897" /><part name="55" x="610" y="970" /><part name="56" x="587" y="1025" /><part name="57" x="532" y="1050" /><part name="58" x="477" y="1030" /><part name="59" x="449" y="980" /><part name="60" x="434" y="898" /><part name="61" x="475" y="950" /><part name="62" x="527" y="982" /><part name="63" x="572" y="961" /><part name="64" x="598" y="901" /><part name="65" x="570" y="873" /><part name="66" x="524" y="881" /><part name="67" x="481" y="870" /></box></image><image file="images/robshapes2_frame270.jpg"><box top="100" left="100" width="880" height="1000"><part name="00" x="223" y="495" /><part name="01" x="226" y="573" /><part name="02" x="241" y="652" /><part name="03" x="254" y="729" /><part name="04" x="289" y="805" /><part name="05" x="334" y="866" /><part name="06" x="374" y="940" /><part name="07" x="452" y="997" /><part name="08" x="536" y="1013" /><part name="09" x="627" y="994" /><part name="10" x="676" y="943" /><part name="11" x="720" y="876" /><part name="12" x="766" y="809" /><part name="13" x="788" y="733" /><part name="14" x="802" y="650" /><part name="15" x="807" y="571" /><part name="16" x="808" y="484" /><part name="17" x="255" y="474" /><part name="18" x="287" y="433" /><part name="19" x="330" y="432" /><part name="20" x="392" y="433" /><part name="21" x="456" y="448" /><part name="22" x="562" y="456" /><part name="23" x="622" y="437" /><part name="24" x="682" y="428" /><part name="25" x="738" y="439" /><part name="26" x="779" y="476" /><part name="27" x="523" y="525" /><part name="28" x="528" y="595" /><part name="29" x="532" y="665" /><part name="30" x="533" y="738" /><part name="31" x="447" y="742" /><part name="32" x="487" y="757" /><part name="33" x="533" y="776" /><part name="34" x="575" y="758" /><part name="35" x="612" y="739" /><part name="36" x="324" y="523" /><part name="37" x="363" y="498" /><part name="38" x="413" y="498" /><part name="39" x="452" y="532" /><part name="40" x="415" y="550" /><part name="41" x="366" y="549" /><part name="42" x="598" y="522" /><part name="43" x="640" y="498" /><part name="44" x="681" y="498" /><part name="45" x="717" y="518" /><part name="46" x="684" y="542" /><part name="47" x="641" y="544" /><part name="48" x="387" y="758" /><part name="49" x="435" y="773" /><part name="50" x="474" y="786" /><part name="51" x="520" y="797" /><part name="52" x="551" y="787" /><part name="53" x="613" y="775" /><part name="54" x="686" y="755" /><part name="55" x="619" y="818" /><part name="56" x="573" y="832" /><part name="57" x="533" y="842" /><part name="58" x="489" y="837" /><part name="59" x="432" y="812" /><part name="60" x="386" y="761" /><part name="61" x="467" y="798" /><part name="62" x="537" y="806" /><part name="63" x="586" y="798" /><part name="64" x="670" y="762" /><part name="65" x="585" y="797" /><part name="66" x="537" y="806" /><part name="67" x="469" y="797" /></box></image><image file="images/robshapes2_frame496.jpg"><box top="100" left="100" width="880" height="1000"><part name="00" x="223" y="495" /><part name="01" x="226" y="574" /><part name="02" x="241" y="656" /><part name="03" x="254" y="735" /><part name="04" x="289" y="813" /><part name="05" x="329" y="878" /><part name="06" x="374" y="953" /><part name="07" x="452" y="1013" /><part name="08" x="536" y="1031" /><part name="09" x="627" y="1009" /><part name="10" x="676" y="957" /><part name="11" x="720" y="886" /><part name="12" x="766" y="817" /><part name="13" x="788" y="739" /><part name="14" x="802" y="654" /><part name="15" x="807" y="573" /><part name="16" x="808" y="484" /><part name="17" x="255" y="474" /><part name="18" x="287" y="433" /><part name="19" x="330" y="432" /><part name="20" x="392" y="433" /><part name="21" x="456" y="448" /><part name="22" x="562" y="456" /><part name="23" x="622" y="437" /><part name="24" x="682" y="428" /><part name="25" x="738" y="439" /><part name="26" x="779" y="476" /><part name="27" x="523" y="514" /><part name="28" x="528" y="584" /><part name="29" x="532" y="654" /><part name="30" x="533" y="727" /><part name="31" x="447" y="731" /><part name="32" x="487" y="746" /><part name="33" x="533" y="765" /><part name="34" x="575" y="747" /><part name="35" x="612" y="728" /><part name="36" x="324" y="523" /><part name="37" x="363" y="498" /><part name="38" x="413" y="498" /><part name="39" x="448" y="520" /><part name="40" x="419" y="544" /><part name="41" x="366" y="549" /><part name="42" x="598" y="522" /><part name="43" x="640" y="498" /><part name="44" x="681" y="498" /><part name="45" x="717" y="518" /><part name="46" x="684" y="542" /><part name="47" x="641" y="544" /><part name="48" x="425" y="837" /><part name="49" x="468" y="828" /><part name="50" x="505" y="827" /><part name="51" x="536" y="835" /><part name="52" x="564" y="826" /><part name="53" x="604" y="829" /><part name="54" x="648" y="838" /><part name="55" x="604" y="879" /><part name="56" x="566" y="893" /><part name="57" x="532" y="901" /><part name="58" x="502" y="893" /><part name="59" x="461" y="879" /><part name="60" x="433" y="840" /><part name="61" x="493" y="854" /><part name="62" x="534" y="860" /><part name="63" x="579" y="851" /><part name="64" x="631" y="837" /><part name="65" x="579" y="851" /><part name="66" x="534" y="860" /><part name="67" x="493" y="854" /></box></image><image file="images/robshapes2_frame571.jpg"><box top="100" left="100" width="880" height="1000"><part name="00" x="223" y="495" /><part name="01" x="227" y="580" /><part name="02" x="243" y="668" /><part name="03" x="267" y="746" /><part name="04" x="300" y="829" /><part name="05" x="328" y="918" /><part name="06" x="392" y="990" /><part name="07" x="461" y="1064" /><part name="08" x="546" y="1089" /><part name="09" x="636" y="1059" /><part name="10" x="684" y="999" /><part name="11" x="726" y="921" /><part name="12" x="771" y="844" /><part name="13" x="791" y="759" /><part name="14" x="804" y="666" /><part name="15" x="808" y="580" /><part name="16" x="808" y="484" /><part name="17" x="260" y="463" /><part name="18" x="292" y="422" /><part name="19" x="335" y="421" /><part name="20" x="397" y="422" /><part name="21" x="461" y="437" /><part name="22" x="568" y="444" /><part name="23" x="628" y="425" /><part name="24" x="688" y="416" /><part name="25" x="744" y="427" /><part name="26" x="785" y="464" /><part name="27" x="524" y="524" /><part name="28" x="529" y="594" /><part name="29" x="533" y="664" /><part name="30" x="534" y="737" /><part name="31" x="448" y="741" /><part name="32" x="488" y="756" /><part name="33" x="534" y="775" /><part name="34" x="576" y="757" /><part name="35" x="613" y="738" /><part name="36" x="327" y="518" /><part name="37" x="364" y="496" /><part name="38" x="414" y="496" /><part name="39" x="449" y="518" /><part name="40" x="416" y="541" /><part name="41" x="371" y="540" /><part name="42" x="596" y="513" /><part name="43" x="638" y="489" /><part name="44" x="679" y="489" /><part name="45" x="719" y="515" /><part name="46" x="682" y="533" /><part name="47" x="639" y="535" /><part name="48" x="455" y="878" /><part name="49" x="490" y="858" /><part name="50" x="511" y="844" /><part name="51" x="532" y="852" /><part name="52" x="552" y="839" /><part name="53" x="580" y="848" /><part name="54" x="612" y="881" /><part name="55" x="584" y="931" /><part name="56" x="560" y="947" /><part name="57" x="537" y="959" /><part name="58" x="514" y="950" /><part name="59" x="485" y="935" /><part name="60" x="461" y="880" /><part name="61" x="504" y="889" /><part name="62" x="534" y="893" /><part name="63" x="565" y="881" /><part name="64" x="604" y="887" /><part name="65" x="565" y="881" /><part name="66" x="534" y="893" /><part name="67" x="504" y="889" /></box></image><image file="images/robshapes2_frame689.jpg"><box top="100" left="100" width="880" height="1000"><part name="00" x="223" y="495" /><part name="01" x="226" y="573" /><part name="02" x="242" y="653" /><part name="03" x="255" y="731" /><part name="04" x="291" y="807" /><part name="05" x="335" y="867" /><part name="06" x="386" y="934" /><part name="07" x="457" y="1001" /><part name="08" x="541" y="1018" /><part name="09" x="632" y="998" /><part name="10" x="680" y="947" /><part name="11" x="723" y="879" /><part name="12" x="765" y="808" /><part name="13" x="790" y="735" /><part name="14" x="803" y="651" /><part name="15" x="807" y="572" /><part name="16" x="808" y="484" /><part name="17" x="259" y="422" /><part name="18" x="268" y="355" /><part name="19" x="321" y="341" /><part name="20" x="383" y="342" /><part name="21" x="447" y="357" /><part name="22" x="586" y="356" /><part name="23" x="646" y="337" /><part name="24" x="706" y="328" /><part name="25" x="762" y="349" /><part name="26" x="784" y="406" /><part name="27" x="522" y="500" /><part name="28" x="527" y="570" /><part name="29" x="531" y="640" /><part name="30" x="532" y="713" /><part name="31" x="446" y="717" /><part name="32" x="486" y="732" /><part name="33" x="532" y="751" /><part name="34" x="574" y="733" /><part name="35" x="611" y="714" /><part name="36" x="331" y="503" /><part name="37" x="368" y="471" /><part name="38" x="416" y="474" /><part name="39" x="455" y="500" /><part name="40" x="422" y="530" /><part name="41" x="373" y="529" /><part name="42" x="593" y="500" /><part name="43" x="633" y="471" /><part name="44" x="681" y="464" /><part name="45" x="712" y="496" /><part name="46" x="679" y="520" /><part name="47" x="636" y="522" /><part name="48" x="424" y="822" /><part name="49" x="467" y="815" /><part name="50" x="504" y="816" /><part name="51" x="536" y="825" /><part name="52" x="564" y="816" /><part name="53" x="604" y="819" /><part name="54" x="649" y="830" /><part name="55" x="604" y="869" /><part name="56" x="566" y="883" /><part name="57" x="532" y="891" /><part name="58" x="501" y="882" /><part name="59" x="460" y="866" /><part name="60" x="433" y="825" /><part name="61" x="493" y="843" /><part name="62" x="534" y="850" /><part name="63" x="578" y="842" /><part name="64" x="640" y="829" /><part name="65" x="578" y="842" /><part name="66" x="534" y="850" /><part name="67" x="493" y="843" /></box></image><image file="images/robshapes2_frame799.jpg"><box top="100" left="100" width="880" height="1000"><part name="00" x="228" y="496" /><part name="01" x="237" y="572" /><part name="02" x="253" y="655" /><part name="03" x="265" y="731" /><part name="04" x="290" y="809" /><part name="05" x="330" y="873" /><part name="06" x="373" y="946" /><part name="07" x="450" y="1005" /><part name="08" x="533" y="1022" /><part name="09" x="624" y="1000" /><part name="10" x="672" y="949" /><part name="11" x="716" y="880" /><part name="12" x="747" y="808" /><part name="13" x="784" y="734" /><part name="14" x="797" y="650" /><part name="15" x="802" y="570" /><part name="16" x="804" y="482" /><part name="17" x="267" y="490" /><part name="18" x="314" y="443" /><part name="19" x="361" y="443" /><part name="20" x="404" y="449" /><part name="21" x="458" y="467" /><part name="22" x="572" y="466" /><part name="23" x="632" y="447" /><part name="24" x="675" y="433" /><part name="25" x="734" y="445" /><part name="26" x="771" y="482" /><part name="27" x="516" y="497" /><part name="28" x="521" y="567" /><part name="29" x="525" y="637" /><part name="30" x="526" y="710" /><part name="31" x="440" y="714" /><part name="32" x="480" y="729" /><part name="33" x="526" y="748" /><part name="34" x="568" y="730" /><part name="35" x="605" y="711" /><part name="36" x="324" y="523" /><part name="37" x="363" y="505" /><part name="38" x="411" y="510" /><part name="39" x="448" y="520" /><part name="40" x="408" y="525" /><part name="41" x="363" y="530" /><part name="42" x="596" y="513" /><part name="43" x="640" y="498" /><part name="44" x="681" y="498" /><part name="45" x="715" y="513" /><part name="46" x="677" y="523" /><part name="47" x="639" y="527" /><part name="48" x="413" y="820" /><part name="49" x="458" y="811" /><part name="50" x="496" y="810" /><part name="51" x="528" y="818" /><part name="52" x="557" y="809" /><part name="53" x="599" y="812" /><part name="54" x="644" y="822" /><part name="55" x="599" y="862" /><part name="56" x="559" y="876" /><part name="57" x="524" y="884" /><part name="58" x="493" y="876" /><part name="59" x="451" y="862" /><part name="60" x="427" y="822" /><part name="61" x="484" y="837" /><part name="62" x="526" y="843" /><part name="63" x="572" y="835" /><part name="64" x="635" y="822" /><part name="65" x="572" y="835" /><part name="66" x="526" y="843" /><part name="67" x="484" y="837" /></box></image><image file="images/robshapes2_frame955.jpg"><box top="100" left="100" width="880" height="1000"><part name="00" x="234" y="495" /><part name="01" x="235" y="572" /><part name="02" x="254" y="646" /><part name="03" x="275" y="723" /><part name="04" x="304" y="801" /><part name="05" x="337" y="864" /><part name="06" x="384" y="931" /><part name="07" x="458" y="996" /><part name="08" x="541" y="1012" /><part name="09" x="632" y="993" /><part name="10" x="680" y="943" /><part name="11" x="718" y="875" /><part name="12" x="753" y="806" /><part name="13" x="783" y="733" /><part name="14" x="803" y="650" /><part name="15" x="807" y="571" /><part name="16" x="808" y="484" /><part name="17" x="262" y="458" /><part name="18" x="294" y="417" /><part name="19" x="337" y="416" /><part name="20" x="399" y="417" /><part name="21" x="463" y="432" /><part name="22" x="568" y="437" /><part name="23" x="628" y="418" /><part name="24" x="688" y="409" /><part name="25" x="744" y="420" /><part name="26" x="785" y="457" /><part name="27" x="523" y="491" /><part name="28" x="528" y="561" /><part name="29" x="532" y="631" /><part name="30" x="533" y="704" /><part name="31" x="447" y="708" /><part name="32" x="487" y="723" /><part name="33" x="533" y="742" /><part name="34" x="575" y="724" /><part name="35" x="612" y="705" /><part name="36" x="330" y="506" /><part name="37" x="369" y="481" /><part name="38" x="419" y="481" /><part name="39" x="454" y="503" /><part name="40" x="421" y="533" /><part name="41" x="372" y="532" /><part name="42" x="592" y="502" /><part name="43" x="634" y="478" /><part name="44" x="675" y="478" /><part name="45" x="711" y="498" /><part name="46" x="678" y="522" /><part name="47" x="635" y="524" /><part name="48" x="425" y="814" /><part name="49" x="468" y="807" /><part name="50" x="505" y="807" /><part name="51" x="536" y="816" /><part name="52" x="565" y="807" /><part name="53" x="604" y="810" /><part name="54" x="649" y="820" /><part name="55" x="610" y="864" /><part name="56" x="567" y="874" /><part name="57" x="532" y="882" /><part name="58" x="502" y="873" /><part name="59" x="461" y="858" /><part name="60" x="434" y="818" /><part name="61" x="494" y="834" /><part name="62" x="534" y="841" /><part name="63" x="579" y="832" /><part name="64" x="640" y="819" /><part name="65" x="579" y="832" /><part name="66" x="534" y="840" /><part name="67" x="494" y="834" /></box></image><image file="images/robshapes2_frame462.jpg"><box top="100" left="100" width="880" height="1000"><part name="00" x="223" y="495" /><part name="01" x="225" y="579" /><part name="02" x="240" y="666" /><part name="03" x="262" y="745" /><part name="04" x="301" y="827" /><part name="05" x="343" y="903" /><part name="06" x="383" y="984" /><part name="07" x="457" y="1055" /><part name="08" x="541" y="1078" /><part name="09" x="632" y="1050" /><part name="10" x="681" y="992" /><part name="11" x="724" y="915" /><part name="12" x="771" y="840" /><part name="13" x="789" y="755" /><part name="14" x="805" y="665" /><part name="15" x="809" y="579" /><part name="16" x="810" y="485" /><part name="17" x="264" y="471" /><part name="18" x="288" y="429" /><part name="19" x="337" y="418" /><part name="20" x="399" y="431" /><part name="21" x="460" y="449" /><part name="22" x="579" y="451" /><part name="23" x="634" y="432" /><part name="24" x="698" y="419" /><part name="25" x="745" y="434" /><part name="26" x="784" y="477" /><part name="27" x="531" y="519" /><part name="28" x="536" y="589" /><part name="29" x="540" y="660" /><part name="30" x="541" y="733" /><part name="31" x="455" y="737" /><part name="32" x="495" y="752" /><part name="33" x="541" y="771" /><part name="34" x="584" y="753" /><part name="35" x="621" y="734" /><part name="36" x="334" y="522" /><part name="37" x="373" y="505" /><part name="38" x="421" y="503" /><part name="39" x="458" y="524" /><part name="40" x="420" y="549" /><part name="41" x="369" y="551" /><part name="42" x="598" y="522" /><part name="43" x="639" y="496" /><part name="44" x="680" y="497" /><part name="45" x="719" y="519" /><part name="46" x="686" y="544" /><part name="47" x="641" y="546" /><part name="48" x="441" y="873" /><part name="49" x="483" y="852" /><part name="50" x="514" y="843" /><part name="51" x="541" y="851" /><part name="52" x="567" y="837" /><part name="53" x="602" y="844" /><part name="54" x="641" y="866" /><part name="55" x="616" y="927" /><part name="56" x="579" y="947" /><part name="57" x="542" y="962" /><part name="58" x="507" y="950" /><part name="59" x="474" y="930" /><part name="60" x="464" y="870" /><part name="61" x="500" y="894" /><part name="62" x="540" y="905" /><part name="63" x="582" y="891" /><part name="64" x="618" y="872" /><part name="65" x="583" y="863" /><part name="66" x="543" y="869" /><part name="67" x="506" y="864" /></box></image><image file="images/robshapes2_frame449.jpg"><box top="100" left="100" width="880" height="1000"><part name="00" x="221" y="495" /><part name="01" x="225" y="581" /><part name="02" x="240" y="671" /><part name="03" x="264" y="749" /><part name="04" x="301" y="832" /><part name="05" x="332" y="919" /><part name="06" x="386" y="996" /><part name="07" x="457" y="1068" /><part name="08" x="542" y="1094" /><part name="09" x="633" y="1063" /><part name="10" x="681" y="1003" /><part name="11" x="725" y="924" /><part name="12" x="770" y="847" /><part name="13" x="790" y="760" /><part name="14" x="804" y="667" /><part name="15" x="808" y="581" /><part name="16" x="809" y="484" /><part name="17" x="258" y="475" /><part name="18" x="292" y="436" /><part name="19" x="335" y="436" /><part name="20" x="396" y="437" /><part name="21" x="460" y="452" /><part name="22" x="564" y="460" /><part name="23" x="624" y="441" /><part name="24" x="684" y="432" /><part name="25" x="740" y="442" /><part name="26" x="782" y="478" /><part name="27" x="523" y="531" /><part name="28" x="528" y="601" /><part name="29" x="532" y="671" /><part name="30" x="533" y="744" /><part name="31" x="447" y="748" /><part name="32" x="487" y="763" /><part name="33" x="533" y="783" /><part name="34" x="576" y="764" /><part name="35" x="613" y="745" /><part name="36" x="325" y="525" /><part name="37" x="362" y="503" /><part name="38" x="413" y="503" /><part name="39" x="448" y="527" /><part name="40" x="415" y="547" /><part name="41" x="368" y="547" /><part name="42" x="599" y="521" /><part name="43" x="639" y="498" /><part name="44" x="682" y="499" /><part name="45" x="721" y="522" /><part name="46" x="685" y="541" /><part name="47" x="642" y="543" /><part name="48" x="429" y="872" /><part name="49" x="461" y="835" /><part name="50" x="499" y="818" /><part name="51" x="531" y="830" /><part name="52" x="569" y="809" /><part name="53" x="614" y="827" /><part name="54" x="639" y="883" /><part name="55" x="617" y="950" /><part name="56" x="576" y="985" /><part name="57" x="526" y="992" /><part name="58" x="486" y="980" /><part name="59" x="448" y="944" /><part name="60" x="482" y="883" /><part name="61" x="493" y="912" /><part name="62" x="535" y="932" /><part name="63" x="578" y="913" /><part name="64" x="588" y="887" /><part name="65" x="575" y="853" /><part name="66" x="534" y="848" /><part name="67" x="490" y="849" /></box></image><image file="images/robshapes2_frame172.jpg"><box top="100" left="100" width="880" height="1000"><part name="00" x="223" y="495" /><part name="01" x="225" y="583" /><part name="02" x="240" y="674" /><part name="03" x="267" y="756" /><part name="04" x="311" y="840" /><part name="05" x="340" y="928" /><part name="06" x="380" y="1009" /><part name="07" x="455" y="1088" /><part name="08" x="539" y="1115" /><part name="09" x="630" y="1081" /><part name="10" x="678" y="1019" /><part name="11" x="722" y="936" /><part name="12" x="761" y="854" /><part name="13" x="784" y="766" /><part name="14" x="802" y="672" /><part name="15" x="807" y="582" /><part name="16" x="809" y="485" /><part name="17" x="255" y="472" /><part name="18" x="286" y="432" /><part name="19" x="328" y="431" /><part name="20" x="392" y="432" /><part name="21" x="457" y="446" /><part name="22" x="562" y="455" /><part name="23" x="622" y="436" /><part name="24" x="683" y="427" /><part name="25" x="739" y="438" /><part name="26" x="781" y="475" /><part name="27" x="519" y="528" /><part name="28" x="524" y="598" /><part name="29" x="528" y="668" /><part name="30" x="529" y="741" /><part name="31" x="443" y="745" /><part name="32" x="483" y="760" /><part name="33" x="529" y="779" /><part name="34" x="572" y="761" /><part name="35" x="609" y="742" /><part name="36" x="325" y="522" /><part name="37" x="364" y="497" /><part name="38" x="414" y="496" /><part name="39" x="449" y="520" /><part name="40" x="417" y="551" /><part name="41" x="367" y="550" /><part name="42" x="598" y="522" /><part name="43" x="635" y="496" /><part name="44" x="681" y="497" /><part name="45" x="717" y="518" /><part name="46" x="685" y="543" /><part name="47" x="641" y="545" /><part name="48" x="424" y="888" /><part name="49" x="465" y="851" /><part name="50" x="499" y="844" /><part name="51" x="529" y="860" /><part name="52" x="558" y="840" /><part name="53" x="595" y="848" /><part name="54" x="635" y="892" /><part name="55" x="611" y="968" /><part name="56" x="586" y="1023" /><part name="57" x="533" y="1048" /><part name="58" x="480" y="1027" /><part name="59" x="450" y="977" /><part name="60" x="447" y="905" /><part name="61" x="472" y="957" /><part name="62" x="529" y="991" /><part name="63" x="585" y="964" /><part name="64" x="604" y="897" /><part name="65" x="572" y="872" /><part name="66" x="526" y="880" /><part name="67" x="483" y="870" /></box></image><image file="images/robshapes2_frame888.jpg"><box top="100" left="100" width="880" height="1000"><part name="00" x="231" y="496" /><part name="01" x="234" y="573" /><part name="02" x="251" y="650" /><part name="03" x="268" y="728" /><part name="04" x="298" y="806" /><part name="05" x="332" y="871" /><part name="06" x="379" y="939" /><part name="07" x="455" y="1002" /><part name="08" x="538" y="1018" /><part name="09" x="629" y="998" /><part name="10" x="677" y="948" /><part name="11" x="718" y="879" /><part name="12" x="754" y="809" /><part name="13" x="784" y="735" /><part name="14" x="802" y="651" /><part name="15" x="806" y="572" /><part name="16" x="808" y="484" /><part name="17" x="262" y="465" /><part name="18" x="295" y="421" /><part name="19" x="340" y="419" /><part name="20" x="398" y="421" /><part name="21" x="460" y="437" /><part name="22" x="569" y="440" /><part name="23" x="629" y="421" /><part name="24" x="686" y="411" /><part name="25" x="742" y="423" /><part name="26" x="781" y="462" /><part name="27" x="520" y="501" /><part name="28" x="525" y="571" /><part name="29" x="529" y="640" /><part name="30" x="530" y="713" /><part name="31" x="444" y="717" /><part name="32" x="484" y="733" /><part name="33" x="530" y="752" /><part name="34" x="572" y="734" /><part name="35" x="609" y="714" /><part name="36" x="327" y="525" /><part name="37" x="370" y="537" /><part name="38" x="417" y="536" /><part name="39" x="452" y="509" /><part name="40" x="417" y="535" /><part name="41" x="369" y="535" /><part name="42" x="594" y="508" /><part name="43" x="627" y="533" /><part name="44" x="673" y="532" /><part name="45" x="711" y="525" /><part name="46" x="673" y="536" /><part name="47" x="632" y="534" /><part name="48" x="416" y="821" /><part name="49" x="460" y="813" /><part name="50" x="499" y="814" /><part name="51" x="532" y="823" /><part name="52" x="562" y="814" /><part name="53" x="603" y="817" /><part name="54" x="649" y="827" /><part name="55" x="606" y="868" /><part name="56" x="564" y="880" /><part name="57" x="527" y="888" /><part name="58" x="495" y="879" /><part name="59" x="453" y="864" /><part name="60" x="426" y="824" /><part name="61" x="487" y="841" /><part name="62" x="529" y="848" /><part name="63" x="576" y="840" /><part name="64" x="641" y="826" /><part name="65" x="576" y="839" /><part name="66" x="529" y="846" /><part name="67" x="487" y="840" /></box></image><image file="images/robshapes2_frame37.jpg"><box top="100" left="100" width="880" height="1000"><part name="00" x="221" y="496" /><part name="01" x="226" y="576" /><part name="02" x="240" y="661" /><part name="03" x="248" y="741" /><part name="04" x="284" y="821" /><part name="05" x="317" y="893" /><part name="06" x="364" y="965" /><part name="07" x="446" y="1023" /><part name="08" x="528" y="1042" /><part name="09" x="619" y="1018" /><part name="10" x="670" y="950" /><part name="11" x="706" y="889" /><part name="12" x="750" y="818" /><part name="13" x="775" y="740" /><part name="14" x="798" y="655" /><part name="15" x="804" y="575" /><part name="16" x="806" y="484" /><part name="17" x="253" y="489" /><part name="18" x="292" y="447" /><part name="19" x="335" y="449" /><part name="20" x="391" y="449" /><part name="21" x="452" y="464" /><part name="22" x="557" y="472" /><part name="23" x="618" y="453" /><part name="24" x="671" y="443" /><part name="25" x="730" y="454" /><part name="26" x="771" y="489" /><part name="27" x="508" y="541" /><part name="28" x="513" y="611" /><part name="29" x="517" y="679" /><part name="30" x="518" y="752" /><part name="31" x="431" y="756" /><part name="32" x="472" y="771" /><part name="33" x="518" y="790" /><part name="34" x="558" y="772" /><part name="35" x="595" y="753" /><part name="36" x="319" y="532" /><part name="37" x="359" y="510" /><part name="38" x="409" y="512" /><part name="39" x="444" y="535" /><part name="40" x="409" y="552" /><part name="41" x="361" y="552" /><part name="42" x="587" y="536" /><part name="43" x="628" y="520" /><part name="44" x="671" y="520" /><part name="45" x="704" y="543" /><part name="46" x="671" y="556" /><part name="47" x="630" y="556" /><part name="48" x="404" y="855" /><part name="49" x="445" y="847" /><part name="50" x="482" y="846" /><part name="51" x="514" y="854" /><part name="52" x="540" y="845" /><part name="53" x="579" y="849" /><part name="54" x="624" y="859" /><part name="55" x="580" y="896" /><part name="56" x="543" y="908" /><part name="57" x="511" y="916" /><part name="58" x="480" y="908" /><part name="59" x="439" y="895" /><part name="60" x="411" y="858" /><part name="61" x="471" y="871" /><part name="62" x="512" y="877" /><part name="63" x="555" y="869" /><part name="64" x="615" y="858" /><part name="65" x="555" y="869" /><part name="66" x="512" y="877" /><part name="67" x="471" y="871" /></box></image><image file="images/roblots_frame60.jpg"><box top="100" left="100" width="880" height="1000"><part name="00" x="235" y="494" /><part name="01" x="237" y="575" /><part name="02" x="253" y="657" /><part name="03" x="274" y="734" /><part name="04" x="309" y="813" /><part name="05" x="344" y="888" /><part name="06" x="394" y="960" /><part name="07" x="467" y="1025" /><part name="08" x="552" y="1047" /><part name="09" x="642" y="1023" /><part name="10" x="691" y="968" /><part name="11" x="733" y="896" /><part name="12" x="778" y="826" /><part name="13" x="798" y="745" /><part name="14" x="813" y="658" /><part name="15" x="818" y="576" /><part name="16" x="819" y="486" /><part name="17" x="259" y="470" /><part name="18" x="291" y="430" /><part name="19" x="335" y="428" /><part name="20" x="397" y="431" /><part name="21" x="460" y="447" /><part name="22" x="577" y="449" /><part name="23" x="637" y="430" /><part name="24" x="698" y="420" /><part name="25" x="752" y="431" /><part name="26" x="794" y="468" /><part name="27" x="525" y="519" /><part name="28" x="530" y="590" /><part name="29" x="534" y="660" /><part name="30" x="535" y="733" /><part name="31" x="449" y="737" /><part name="32" x="489" y="752" /><part name="33" x="535" y="771" /><part name="34" x="578" y="753" /><part name="35" x="615" y="734" /><part name="36" x="328" y="518" /><part name="37" x="365" y="489" /><part name="38" x="416" y="489" /><part name="39" x="452" y="522" /><part name="40" x="418" y="545" /><part name="41" x="369" y="545" /><part name="42" x="597" y="518" /><part name="43" x="640" y="485" /><part name="44" x="681" y="486" /><part name="45" x="719" y="513" /><part name="46" x="685" y="536" /><part name="47" x="641" y="539" /><part name="48" x="436" y="830" /><part name="49" x="477" y="823" /><part name="50" x="511" y="821" /><part name="51" x="542" y="830" /><part name="52" x="572" y="816" /><part name="53" x="614" y="819" /><part name="54" x="655" y="830" /><part name="55" x="619" y="887" /><part name="56" x="580" y="910" /><part name="57" x="543" y="919" /><part name="58" x="507" y="908" /><part name="59" x="467" y="885" /><part name="60" x="455" y="836" /><part name="61" x="500" y="860" /><part name="62" x="545" y="871" /><part name="63" x="586" y="860" /><part name="64" x="630" y="840" /><part name="65" x="586" y="845" /><part name="66" x="544" y="851" /><part name="67" x="500" y="844" /></box></image><image file="images/roblots_frame364.jpg"><box top="100" left="100" width="880" height="1000"><part name="00" x="236" y="494" /><part name="01" x="238" y="575" /><part name="02" x="254" y="656" /><part name="03" x="277" y="732" /><part name="04" x="311" y="811" /><part name="05" x="346" y="885" /><part name="06" x="395" y="956" /><part name="07" x="467" y="1022" /><part name="08" x="552" y="1044" /><part name="09" x="642" y="1020" /><part name="10" x="691" y="966" /><part name="11" x="732" y="894" /><part name="12" x="774" y="824" /><part name="13" x="797" y="744" /><part name="14" x="813" y="657" /><part name="15" x="817" y="576" /><part name="16" x="818" y="486" /><part name="17" x="260" y="468" /><part name="18" x="293" y="428" /><part name="19" x="337" y="426" /><part name="20" x="398" y="428" /><part name="21" x="461" y="444" /><part name="22" x="585" y="446" /><part name="23" x="637" y="427" /><part name="24" x="698" y="418" /><part name="25" x="752" y="428" /><part name="26" x="794" y="465" /><part name="27" x="525" y="516" /><part name="28" x="530" y="587" /><part name="29" x="534" y="657" /><part name="30" x="535" y="730" /><part name="31" x="449" y="734" /><part name="32" x="489" y="749" /><part name="33" x="535" y="768" /><part name="34" x="578" y="750" /><part name="35" x="616" y="731" /><part name="36" x="335" y="514" /><part name="37" x="368" y="500" /><part name="38" x="417" y="496" /><part name="39" x="454" y="521" /><part name="40" x="420" y="535" /><part name="41" x="374" y="536" /><part name="42" x="597" y="514" /><part name="43" x="642" y="486" /><part name="44" x="689" y="483" /><part name="45" x="725" y="514" /><part name="46" x="685" y="532" /><part name="47" x="641" y="535" /><part name="48" x="416" y="800" /><part name="49" x="461" y="800" /><part name="50" x="499" y="802" /><part name="51" x="536" y="814" /><part name="52" x="570" y="801" /><part name="53" x="621" y="802" /><part name="54" x="670" y="810" /><part name="55" x="626" y="873" /><part name="56" x="579" y="901" /><part name="57" x="536" y="908" /><part name="58" x="493" y="895" /><part name="59" x="447" y="863" /><part name="60" x="441" y="811" /><part name="61" x="486" y="845" /><part name="62" x="541" y="862" /><part name="63" x="587" y="850" /><part name="64" x="639" y="821" /><part name="65" x="587" y="826" /><part name="66" x="541" y="831" /><part name="67" x="486" y="820" /></box></image><image file="images/roblots_frame519.jpg"><box top="100" left="100" width="880" height="1000"><part name="00" x="240" y="494" /><part name="01" x="241" y="579" /><part name="02" x="255" y="665" /><part name="03" x="281" y="742" /><part name="04" x="318" y="824" /><part name="05" x="353" y="905" /><part name="06" x="399" y="980" /><part name="07" x="467" y="1054" /><part name="08" x="552" y="1079" /><part name="09" x="642" y="1051" /><part name="10" x="690" y="995" /><part name="11" x="735" y="917" /><part name="12" x="779" y="841" /><part name="13" x="798" y="756" /><part name="14" x="812" y="665" /><part name="15" x="816" y="580" /><part name="16" x="817" y="486" /><part name="17" x="263" y="458" /><part name="18" x="287" y="413" /><part name="19" x="334" y="406" /><part name="20" x="397" y="412" /><part name="21" x="460" y="429" /><part name="22" x="603" y="426" /><part name="23" x="662" y="407" /><part name="24" x="725" y="397" /><part name="25" x="776" y="411" /><part name="26" x="814" y="454" /><part name="27" x="533" y="513" /><part name="28" x="538" y="583" /><part name="29" x="542" y="654" /><part name="30" x="543" y="727" /><part name="31" x="457" y="731" /><part name="32" x="497" y="746" /><part name="33" x="543" y="765" /><part name="34" x="586" y="747" /><part name="35" x="623" y="728" /><part name="36" x="333" y="529" /><part name="37" x="377" y="508" /><part name="38" x="424" y="502" /><part name="39" x="458" y="515" /><part name="40" x="420" y="538" /><part name="41" x="372" y="543" /><part name="42" x="602" y="513" /><part name="43" x="655" y="507" /><part name="44" x="696" y="516" /><part name="45" x="737" y="521" /><part name="46" x="694" y="531" /><part name="47" x="649" y="528" /><part name="48" x="435" y="848" /><part name="49" x="479" y="827" /><part name="50" x="513" y="820" /><part name="51" x="543" y="833" /><part name="52" x="576" y="821" /><part name="53" x="618" y="824" /><part name="54" x="658" y="858" /><part name="55" x="632" y="947" /><part name="56" x="591" y="974" /><part name="57" x="544" y="988" /><part name="58" x="474" y="976" /><part name="59" x="446" y="929" /><part name="60" x="453" y="842" /><part name="61" x="476" y="915" /><part name="62" x="543" y="936" /><part name="63" x="600" y="915" /><part name="64" x="648" y="854" /><part name="65" x="593" y="842" /><part name="66" x="541" y="847" /><part name="67" x="501" y="845" /></box></image><image file="images/roblots_frame682.jpg"><box top="100" left="100" width="880" height="1000"><part name="00" x="229" y="495" /><part name="01" x="231" y="576" /><part name="02" x="247" y="659" /><part name="03" x="263" y="737" /><part name="04" x="300" y="816" /><part name="05" x="334" y="889" /><part name="06" x="382" y="961" /><part name="07" x="458" y="1025" /><part name="08" x="542" y="1045" /><part name="09" x="633" y="1021" /><part name="10" x="682" y="964" /><part name="11" x="724" y="894" /><part name="12" x="768" y="823" /><part name="13" x="790" y="744" /><part name="14" x="807" y="657" /><part name="15" x="812" y="576" /><part name="16" x="814" y="485" /><part name="17" x="243" y="467" /><part name="18" x="274" y="419" /><part name="19" x="330" y="417" /><part name="20" x="378" y="427" /><part name="21" x="439" y="439" /><part name="22" x="578" y="445" /><part name="23" x="639" y="426" /><part name="24" x="698" y="417" /><part name="25" x="755" y="429" /><part name="26" x="795" y="466" /><part name="27" x="519" y="525" /><part name="28" x="524" y="596" /><part name="29" x="528" y="665" /><part name="30" x="529" y="738" /><part name="31" x="443" y="742" /><part name="32" x="483" y="757" /><part name="33" x="529" y="776" /><part name="34" x="571" y="758" /><part name="35" x="608" y="739" /><part name="36" x="325" y="520" /><part name="37" x="354" y="499" /><part name="38" x="405" y="494" /><part name="39" x="449" y="523" /><part name="40" x="416" y="547" /><part name="41" x="360" y="547" /><part name="42" x="595" y="522" /><part name="43" x="638" y="488" /><part name="44" x="680" y="488" /><part name="45" x="715" y="517" /><part name="46" x="684" y="538" /><part name="47" x="640" y="535" /><part name="48" x="419" y="837" /><part name="49" x="461" y="827" /><part name="50" x="499" y="826" /><part name="51" x="532" y="836" /><part name="52" x="563" y="824" /><part name="53" x="606" y="827" /><part name="54" x="650" y="841" /><part name="55" x="614" y="896" /><part name="56" x="579" y="922" /><part name="57" x="531" y="926" /><part name="58" x="486" y="922" /><part name="59" x="451" y="891" /><part name="60" x="454" y="840" /><part name="61" x="486" y="869" /><part name="62" x="533" y="877" /><part name="63" x="578" y="868" /><part name="64" x="602" y="846" /><part name="65" x="577" y="844" /><part name="66" x="532" y="850" /><part name="67" x="487" y="836" /></box></image><image file="images/roblots_frame1311.jpg"><box top="100" left="100" width="880" height="1000"><part name="00" x="246" y="494" /><part name="01" x="246" y="577" /><part name="02" x="259" y="662" /><part name="03" x="278" y="740" /><part name="04" x="314" y="820" /><part name="05" x="349" y="897" /><part name="06" x="391" y="974" /><part name="07" x="463" y="1040" /><part name="08" x="546" y="1064" /><part name="09" x="636" y="1038" /><part name="10" x="686" y="981" /><part name="11" x="731" y="907" /><part name="12" x="767" y="829" /><part name="13" x="797" y="751" /><part name="14" x="814" y="662" /><part name="15" x="819" y="578" /><part name="16" x="822" y="486" /><part name="17" x="267" y="485" /><part name="18" x="298" y="430" /><part name="19" x="342" y="427" /><part name="20" x="406" y="432" /><part name="21" x="469" y="448" /><part name="22" x="597" y="460" /><part name="23" x="656" y="441" /><part name="24" x="719" y="431" /><part name="25" x="772" y="442" /><part name="26" x="815" y="479" /><part name="27" x="526" y="530" /><part name="28" x="531" y="600" /><part name="29" x="535" y="670" /><part name="30" x="536" y="744" /><part name="31" x="450" y="748" /><part name="32" x="490" y="763" /><part name="33" x="536" y="782" /><part name="34" x="579" y="764" /><part name="35" x="616" y="745" /><part name="36" x="336" y="534" /><part name="37" x="368" y="512" /><part name="38" x="416" y="510" /><part name="39" x="456" y="536" /><part name="40" x="417" y="553" /><part name="41" x="368" y="553" /><part name="42" x="610" y="536" /><part name="43" x="651" y="510" /><part name="44" x="693" y="511" /><part name="45" x="731" y="533" /><part name="46" x="698" y="557" /><part name="47" x="656" y="555" /><part name="48" x="396" y="805" /><part name="49" x="447" y="809" /><part name="50" x="488" y="817" /><part name="51" x="531" y="831" /><part name="52" x="572" y="822" /><part name="53" x="620" y="810" /><part name="54" x="678" y="805" /><part name="55" x="632" y="881" /><part name="56" x="586" y="915" /><part name="57" x="538" y="931" /><part name="58" x="486" y="914" /><part name="59" x="436" y="877" /><part name="60" x="414" y="814" /><part name="61" x="471" y="866" /><part name="62" x="537" y="886" /><part name="63" x="592" y="868" /><part name="64" x="645" y="823" /><part name="65" x="589" y="836" /><part name="66" x="536" y="844" /><part name="67" x="476" y="831" /></box></image><image file="images/roblots_frame1361.jpg"><box top="100" left="100" width="880" height="1000"><part name="00" x="245" y="494" /><part name="01" x="244" y="578" /><part name="02" x="257" y="663" /><part name="03" x="277" y="741" /><part name="04" x="314" y="822" /><part name="05" x="351" y="898" /><part name="06" x="391" y="978" /><part name="07" x="464" y="1043" /><part name="08" x="547" y="1067" /><part name="09" x="638" y="1041" /><part name="10" x="690" y="985" /><part name="11" x="736" y="910" /><part name="12" x="777" y="834" /><part name="13" x="804" y="754" /><part name="14" x="823" y="665" /><part name="15" x="829" y="580" /><part name="16" x="833" y="489" /><part name="17" x="272" y="490" /><part name="18" x="296" y="438" /><part name="19" x="340" y="434" /><part name="20" x="406" y="442" /><part name="21" x="470" y="458" /><part name="22" x="611" y="470" /><part name="23" x="654" y="452" /><part name="24" x="720" y="442" /><part name="25" x="778" y="452" /><part name="26" x="815" y="496" /><part name="27" x="551" y="558" /><part name="28" x="553" y="628" /><part name="29" x="557" y="695" /><part name="30" x="562" y="759" /><part name="31" x="475" y="777" /><part name="32" x="515" y="792" /><part name="33" x="561" y="811" /><part name="34" x="604" y="793" /><part name="35" x="641" y="774" /><part name="36" x="343" y="543" /><part name="37" x="375" y="523" /><part name="38" x="424" y="519" /><part name="39" x="463" y="544" /><part name="40" x="425" y="562" /><part name="41" x="379" y="560" /><part name="42" x="617" y="548" /><part name="43" x="658" y="521" /><part name="44" x="698" y="523" /><part name="45" x="738" y="543" /><part name="46" x="706" y="564" /><part name="47" x="663" y="557" /><part name="48" x="446" y="862" /><part name="49" x="492" y="859" /><part name="50" x="529" y="858" /><part name="51" x="560" y="866" /><part name="52" x="588" y="852" /><part name="53" x="629" y="844" /><part name="54" x="673" y="828" /><part name="55" x="636" y="892" /><part name="56" x="598" y="912" /><part name="57" x="552" y="919" /><part name="58" x="522" y="911" /><part name="59" x="481" y="900" /><part name="60" x="455" y="866" /><part name="61" x="515" y="879" /><part name="62" x="556" y="884" /><part name="63" x="600" y="871" /><part name="64" x="664" y="833" /><part name="65" x="600" y="871" /><part name="66" x="556" y="884" /><part name="67" x="515" y="879" /></box></image><image file="images/roblots_frame1419.jpg"><box top="100" left="100" width="880" height="1000"><part name="00" x="245" y="495" /><part name="01" x="246" y="578" /><part name="02" x="259" y="663" /><part name="03" x="280" y="742" /><part name="04" x="314" y="823" /><part name="05" x="350" y="901" /><part name="06" x="389" y="981" /><part name="07" x="463" y="1047" /><part name="08" x="546" y="1071" /><part name="09" x="638" y="1044" /><part name="10" x="688" y="989" /><part name="11" x="737" y="913" /><part name="12" x="776" y="836" /><part name="13" x="804" y="755" /><part name="14" x="821" y="666" /><part name="15" x="827" y="581" /><part name="16" x="832" y="489" /><part name="17" x="277" y="497" /><part name="18" x="306" y="454" /><part name="19" x="349" y="453" /><part name="20" x="411" y="462" /><part name="21" x="472" y="479" /><part name="22" x="616" y="490" /><part name="23" x="660" y="471" /><part name="24" x="723" y="459" /><part name="25" x="774" y="468" /><part name="26" x="816" y="505" /><part name="27" x="552" y="558" /><part name="28" x="557" y="628" /><part name="29" x="561" y="699" /><part name="30" x="562" y="773" /><part name="31" x="476" y="777" /><part name="32" x="516" y="792" /><part name="33" x="562" y="811" /><part name="34" x="605" y="793" /><part name="35" x="642" y="774" /><part name="36" x="353" y="544" /><part name="37" x="388" y="525" /><part name="38" x="436" y="527" /><part name="39" x="476" y="550" /><part name="40" x="436" y="558" /><part name="41" x="384" y="562" /><part name="42" x="624" y="545" /><part name="43" x="665" y="525" /><part name="44" x="704" y="524" /><part name="45" x="743" y="552" /><part name="46" x="712" y="566" /><part name="47" x="669" y="564" /><part name="48" x="444" y="874" /><part name="49" x="489" y="866" /><part name="50" x="528" y="866" /><part name="51" x="560" y="876" /><part name="52" x="588" y="864" /><part name="53" x="629" y="864" /><part name="54" x="675" y="868" /><part name="55" x="630" y="917" /><part name="56" x="591" y="934" /><part name="57" x="558" y="946" /><part name="58" x="526" y="935" /><part name="59" x="482" y="919" /><part name="60" x="453" y="876" /><part name="61" x="518" y="884" /><part name="62" x="558" y="891" /><part name="63" x="603" y="890" /><part name="64" x="666" y="868" /><part name="65" x="603" y="890" /><part name="66" x="558" y="891" /><part name="67" x="518" y="884" /></box></image><image file="images/roblots_frame1716.jpg"><box top="100" left="100" width="880" height="1000"><part name="00" x="244" y="494" /><part name="01" x="244" y="580" /><part name="02" x="259" y="670" /><part name="03" x="284" y="748" /><part name="04" x="323" y="832" /><part name="05" x="360" y="917" /><part name="06" x="405" y="999" /><part name="07" x="479" y="1071" /><part name="08" x="565" y="1099" /><part name="09" x="654" y="1067" /><part name="10" x="705" y="1008" /><part name="11" x="751" y="926" /><part name="12" x="792" y="845" /><part name="13" x="817" y="760" /><part name="14" x="831" y="666" /><part name="15" x="835" y="578" /><part name="16" x="839" y="483" /><part name="17" x="268" y="489" /><part name="18" x="299" y="442" /><part name="19" x="344" y="438" /><part name="20" x="408" y="448" /><part name="21" x="471" y="465" /><part name="22" x="608" y="474" /><part name="23" x="665" y="455" /><part name="24" x="732" y="444" /><part name="25" x="780" y="455" /><part name="26" x="818" y="494" /><part name="27" x="560" y="553" /><part name="28" x="565" y="623" /><part name="29" x="569" y="694" /><part name="30" x="570" y="767" /><part name="31" x="484" y="771" /><part name="32" x="524" y="786" /><part name="33" x="570" y="806" /><part name="34" x="614" y="787" /><part name="35" x="651" y="768" /><part name="36" x="357" y="540" /><part name="37" x="391" y="521" /><part name="38" x="440" y="523" /><part name="39" x="474" y="543" /><part name="40" x="436" y="563" /><part name="41" x="390" y="563" /><part name="42" x="631" y="540" /><part name="43" x="674" y="519" /><part name="44" x="714" y="523" /><part name="45" x="756" y="539" /><part name="46" x="721" y="562" /><part name="47" x="677" y="559" /><part name="48" x="438" y="883" /><part name="49" x="483" y="874" /><part name="50" x="518" y="872" /><part name="51" x="552" y="882" /><part name="52" x="589" y="873" /><part name="53" x="628" y="871" /><part name="54" x="669" y="883" /><part name="55" x="637" y="941" /><part name="56" x="593" y="966" /><part name="57" x="549" y="977" /><part name="58" x="499" y="964" /><part name="59" x="464" y="938" /><part name="60" x="469" y="887" /><part name="61" x="500" y="919" /><part name="62" x="549" y="926" /><part name="63" x="589" y="916" /><part name="64" x="632" y="893" /><part name="65" x="593" y="900" /><part name="66" x="548" y="905" /><part name="67" x="505" y="893" /></box></image><image file="images/roblots_frame1872.jpg"><box top="100" left="100" width="880" height="1000"><part name="00" x="244" y="495" /><part name="01" x="244" y="577" /><part name="02" x="257" y="662" /><part name="03" x="276" y="740" /><part name="04" x="311" y="821" /><part name="05" x="349" y="895" /><part name="06" x="390" y="975" /><part name="07" x="465" y="1037" /><part name="08" x="549" y="1061" /><part name="09" x="640" y="1035" /><part name="10" x="691" y="981" /><part name="11" x="740" y="906" /><part name="12" x="782" y="832" /><part name="13" x="808" y="752" /><part name="14" x="824" y="663" /><part name="15" x="830" y="580" /><part name="16" x="834" y="489" /><part name="17" x="272" y="496" /><part name="18" x="301" y="452" /><part name="19" x="344" y="451" /><part name="20" x="407" y="458" /><part name="21" x="470" y="475" /><part name="22" x="611" y="486" /><part name="23" x="657" y="467" /><part name="24" x="721" y="456" /><part name="25" x="774" y="465" /><part name="26" x="814" y="504" /><part name="27" x="553" y="559" /><part name="28" x="557" y="629" /><part name="29" x="561" y="699" /><part name="30" x="563" y="771" /><part name="31" x="477" y="778" /><part name="32" x="517" y="793" /><part name="33" x="563" y="812" /><part name="34" x="606" y="794" /><part name="35" x="643" y="775" /><part name="36" x="349" y="545" /><part name="37" x="384" y="527" /><part name="38" x="433" y="527" /><part name="39" x="472" y="549" /><part name="40" x="434" y="561" /><part name="41" x="383" y="564" /><part name="42" x="623" y="547" /><part name="43" x="665" y="527" /><part name="44" x="704" y="527" /><part name="45" x="743" y="551" /><part name="46" x="711" y="567" /><part name="47" x="668" y="564" /><part name="48" x="443" y="867" /><part name="49" x="487" y="862" /><part name="50" x="528" y="862" /><part name="51" x="562" y="870" /><part name="52" x="592" y="858" /><part name="53" x="636" y="858" /><part name="54" x="679" y="856" /><part name="55" x="635" y="904" /><part name="56" x="592" y="919" /><part name="57" x="554" y="925" /><part name="58" x="523" y="917" /><part name="59" x="478" y="904" /><part name="60" x="459" y="870" /><part name="61" x="520" y="886" /><part name="62" x="561" y="889" /><part name="63" x="603" y="880" /><part name="64" x="669" y="861" /><part name="65" x="603" y="880" /><part name="66" x="561" y="889" /><part name="67" x="520" y="886" /></box></image><image file="images/roblots_frame2274.jpg"><box top="100" left="100" width="880" height="1000"><part name="00" x="226" y="495" /><part name="01" x="229" y="579" /><part name="02" x="245" y="665" /><part name="03" x="264" y="744" /><part name="04" x="302" y="824" /><part name="05" x="335" y="903" /><part name="06" x="383" y="977" /><part name="07" x="457" y="1047" /><part name="08" x="541" y="1069" /><part name="09" x="632" y="1042" /><part name="10" x="681" y="983" /><part name="11" x="724" y="909" /><part name="12" x="766" y="834" /><part name="13" x="789" y="752" /><part name="14" x="805" y="662" /><part name="15" x="810" y="578" /><part name="16" x="812" y="485" /><part name="17" x="250" y="466" /><part name="18" x="280" y="418" /><part name="19" x="332" y="415" /><part name="20" x="385" y="421" /><part name="21" x="447" y="435" /><part name="22" x="575" y="441" /><part name="23" x="636" y="422" /><part name="24" x="695" y="413" /><part name="25" x="752" y="425" /><part name="26" x="791" y="465" /><part name="27" x="521" y="523" /><part name="28" x="526" y="593" /><part name="29" x="530" y="663" /><part name="30" x="531" y="735" /><part name="31" x="445" y="740" /><part name="32" x="485" y="755" /><part name="33" x="531" y="774" /><part name="34" x="573" y="756" /><part name="35" x="610" y="737" /><part name="36" x="325" y="521" /><part name="37" x="358" y="496" /><part name="38" x="409" y="493" /><part name="39" x="449" y="520" /><part name="40" x="416" y="546" /><part name="41" x="363" y="546" /><part name="42" x="597" y="520" /><part name="43" x="639" y="489" /><part name="44" x="681" y="490" /><part name="45" x="717" y="515" /><part name="46" x="685" y="537" /><part name="47" x="641" y="535" /><part name="48" x="425" y="850" /><part name="49" x="467" y="836" /><part name="50" x="502" y="833" /><part name="51" x="531" y="840" /><part name="52" x="561" y="828" /><part name="53" x="600" y="834" /><part name="54" x="637" y="852" /><part name="55" x="604" y="891" /><part name="56" x="571" y="911" /><part name="57" x="523" y="917" /><part name="58" x="479" y="911" /><part name="59" x="450" y="890" /><part name="60" x="454" y="853" /><part name="61" x="487" y="870" /><part name="62" x="524" y="873" /><part name="63" x="570" y="865" /><part name="64" x="598" y="854" /><part name="65" x="570" y="855" /><part name="66" x="525" y="864" /><part name="67" x="488" y="850" /></box></image><image file="images/roblots_frame2367.jpg"><box top="100" left="100" width="880" height="1000"><part name="00" x="234" y="495" /><part name="01" x="236" y="581" /><part name="02" x="249" y="670" /><part name="03" x="267" y="750" /><part name="04" x="306" y="832" /><part name="05" x="340" y="915" /><part name="06" x="387" y="994" /><part name="07" x="462" y="1061" /><part name="08" x="546" y="1086" /><part name="09" x="637" y="1057" /><part name="10" x="688" y="996" /><part name="11" x="733" y="920" /><part name="12" x="778" y="843" /><part name="13" x="800" y="759" /><part name="14" x="817" y="667" /><part name="15" x="822" y="581" /><part name="16" x="825" y="487" /><part name="17" x="259" y="487" /><part name="18" x="288" y="438" /><part name="19" x="337" y="435" /><part name="20" x="395" y="444" /><part name="21" x="457" y="459" /><part name="22" x="594" y="469" /><part name="23" x="649" y="450" /><part name="24" x="711" y="440" /><part name="25" x="766" y="451" /><part name="26" x="806" y="491" /><part name="27" x="536" y="555" /><part name="28" x="540" y="625" /><part name="29" x="544" y="694" /><part name="30" x="546" y="765" /><part name="31" x="460" y="773" /><part name="32" x="500" y="788" /><part name="33" x="546" y="807" /><part name="34" x="588" y="789" /><part name="35" x="625" y="770" /><part name="36" x="335" y="541" /><part name="37" x="367" y="522" /><part name="38" x="417" y="519" /><part name="39" x="457" y="542" /><part name="40" x="421" y="561" /><part name="41" x="370" y="561" /><part name="42" x="611" y="543" /><part name="43" x="653" y="519" /><part name="44" x="693" y="521" /><part name="45" x="732" y="543" /><part name="46" x="700" y="562" /><part name="47" x="656" y="557" /><part name="48" x="433" y="871" /><part name="49" x="473" y="869" /><part name="50" x="509" y="869" /><part name="51" x="541" y="879" /><part name="52" x="572" y="879" /><part name="53" x="606" y="872" /><part name="54" x="648" y="874" /><part name="55" x="615" y="918" /><part name="56" x="580" y="939" /><part name="57" x="538" y="944" /><part name="58" x="497" y="934" /><part name="59" x="463" y="915" /><part name="60" x="456" y="878" /><part name="61" x="497" y="899" /><part name="62" x="538" y="906" /><part name="63" x="584" y="905" /><part name="64" x="640" y="876" /><part name="65" x="583" y="903" /><part name="66" x="539" y="908" /><part name="67" x="496" y="897" /></box></image><image file="images/robvid_frame102.jpg"><box top="100" left="100" width="880" height="1000"><part name="00" x="258" y="498" /><part name="01" x="257" y="580" /><part name="02" x="270" y="662" /><part name="03" x="294" y="738" /><part name="04" x="325" y="818" /><part name="05" x="362" y="890" /><part name="06" x="404" y="966" /><part name="07" x="471" y="1036" /><part name="08" x="553" y="1059" /><part name="09" x="644" y="1034" /><part name="10" x="692" y="984" /><part name="11" x="739" y="906" /><part name="12" x="778" y="831" /><part name="13" x="804" y="751" /><part name="14" x="817" y="662" /><part name="15" x="821" y="578" /><part name="16" x="823" y="487" /><part name="17" x="308" y="477" /><part name="18" x="333" y="430" /><part name="19" x="376" y="424" /><part name="20" x="443" y="429" /><part name="21" x="506" y="447" /><part name="22" x="633" y="454" /><part name="23" x="684" y="435" /><part name="24" x="747" y="424" /><part name="25" x="799" y="436" /><part name="26" x="809" y="478" /><part name="27" x="580" y="517" /><part name="28" x="585" y="588" /><part name="29" x="589" y="659" /><part name="30" x="591" y="731" /><part name="31" x="505" y="737" /><part name="32" x="544" y="752" /><part name="33" x="590" y="771" /><part name="34" x="634" y="753" /><part name="35" x="672" y="734" /><part name="36" x="375" y="523" /><part name="37" x="412" y="497" /><part name="38" x="461" y="497" /><part name="39" x="497" y="524" /><part name="40" x="459" y="543" /><part name="41" x="413" y="545" /><part name="42" x="634" y="519" /><part name="43" x="679" y="490" /><part name="44" x="720" y="490" /><part name="45" x="759" y="515" /><part name="46" x="725" y="528" /><part name="47" x="676" y="527" /><part name="48" x="467" y="842" /><part name="49" x="510" y="833" /><part name="50" x="544" y="831" /><part name="51" x="574" y="842" /><part name="52" x="605" y="829" /><part name="53" x="646" y="829" /><part name="54" x="688" y="839" /><part name="55" x="640" y="901" /><part name="56" x="597" y="923" /><part name="57" x="560" y="935" /><part name="58" x="525" y="923" /><part name="59" x="489" y="899" /><part name="60" x="479" y="848" /><part name="61" x="523" y="877" /><part name="62" x="569" y="881" /><part name="63" x="612" y="868" /><part name="64" x="676" y="845" /><part name="65" x="615" y="861" /><part name="66" x="572" y="863" /><part name="67" x="531" y="857" /></box></image><image file="images/robvid_frame254.jpg"><box top="100" left="100" width="880" height="1000"><part name="00" x="254" y="506" /><part name="01" x="255" y="586" /><part name="02" x="272" y="666" /><part name="03" x="297" y="742" /><part name="04" x="329" y="822" /><part name="05" x="369" y="892" /><part name="06" x="415" y="967" /><part name="07" x="485" y="1035" /><part name="08" x="571" y="1056" /><part name="09" x="658" y="1032" /><part name="10" x="704" y="984" /><part name="11" x="746" y="906" /><part name="12" x="783" y="832" /><part name="13" x="805" y="753" /><part name="14" x="815" y="664" /><part name="15" x="817" y="580" /><part name="16" x="817" y="491" /><part name="17" x="300" y="474" /><part name="18" x="326" y="430" /><part name="19" x="368" y="424" /><part name="20" x="435" y="429" /><part name="21" x="498" y="446" /><part name="22" x="597" y="443" /><part name="23" x="648" y="424" /><part name="24" x="712" y="413" /><part name="25" x="764" y="425" /><part name="26" x="803" y="466" /><part name="27" x="571" y="509" /><part name="28" x="575" y="579" /><part name="29" x="579" y="650" /><part name="30" x="581" y="722" /><part name="31" x="495" y="729" /><part name="32" x="535" y="743" /><part name="33" x="581" y="762" /><part name="34" x="625" y="744" /><part name="35" x="662" y="726" /><part name="36" x="369" y="518" /><part name="37" x="407" y="491" /><part name="38" x="455" y="497" /><part name="39" x="492" y="520" /><part name="40" x="453" y="533" /><part name="41" x="408" y="540" /><part name="42" x="624" y="514" /><part name="43" x="670" y="483" /><part name="44" x="710" y="484" /><part name="45" x="746" y="511" /><part name="46" x="708" y="520" /><part name="47" x="671" y="523" /><part name="48" x="452" y="824" /><part name="49" x="497" y="818" /><part name="50" x="532" y="817" /><part name="51" x="566" y="827" /><part name="52" x="596" y="814" /><part name="53" x="642" y="813" /><part name="54" x="689" y="818" /><part name="55" x="649" y="893" /><part name="56" x="604" y="914" /><part name="57" x="567" y="926" /><part name="58" x="532" y="912" /><part name="59" x="487" y="887" /><part name="60" x="463" y="828" /><part name="61" x="518" y="867" /><part name="62" x="571" y="875" /><part name="63" x="617" y="860" /><part name="64" x="683" y="825" /><part name="65" x="616" y="829" /><part name="66" x="572" y="834" /><part name="67" x="525" y="834" /></box></image><image file="images/robvid_frame101.jpg"><box top="100" left="100" width="880" height="1000"><part name="00" x="258" y="499" /><part name="01" x="258" y="580" /><part name="02" x="275" y="661" /><part name="03" x="300" y="737" /><part name="04" x="333" y="817" /><part name="05" x="373" y="886" /><part name="06" x="418" y="961" /><part name="07" x="489" y="1030" /><part name="08" x="574" y="1053" /><part name="09" x="662" y="1028" /><part name="10" x="707" y="979" /><part name="11" x="750" y="902" /><part name="12" x="787" y="828" /><part name="13" x="810" y="749" /><part name="14" x="822" y="661" /><part name="15" x="824" y="578" /><part name="16" x="824" y="488" /><part name="17" x="309" y="476" /><part name="18" x="333" y="429" /><part name="19" x="376" y="423" /><part name="20" x="443" y="427" /><part name="21" x="507" y="445" /><part name="22" x="631" y="452" /><part name="23" x="682" y="433" /><part name="24" x="745" y="422" /><part name="25" x="797" y="434" /><part name="26" x="808" y="477" /><part name="27" x="581" y="517" /><part name="28" x="586" y="588" /><part name="29" x="590" y="659" /><part name="30" x="592" y="730" /><part name="31" x="506" y="737" /><part name="32" x="545" y="752" /><part name="33" x="591" y="771" /><part name="34" x="635" y="753" /><part name="35" x="673" y="734" /><part name="36" x="375" y="523" /><part name="37" x="413" y="496" /><part name="38" x="462" y="497" /><part name="39" x="498" y="523" /><part name="40" x="460" y="543" /><part name="41" x="414" y="545" /><part name="42" x="634" y="519" /><part name="43" x="678" y="490" /><part name="44" x="719" y="490" /><part name="45" x="758" y="515" /><part name="46" x="724" y="528" /><part name="47" x="676" y="527" /><part name="48" x="469" y="843" /><part name="49" x="512" y="835" /><part name="50" x="547" y="833" /><part name="51" x="576" y="843" /><part name="52" x="606" y="831" /><part name="53" x="646" y="831" /><part name="54" x="688" y="838" /><part name="55" x="639" y="896" /><part name="56" x="596" y="914" /><part name="57" x="561" y="924" /><part name="58" x="530" y="913" /><part name="59" x="493" y="894" /><part name="60" x="478" y="848" /><part name="61" x="531" y="866" /><part name="62" x="572" y="869" /><part name="63" x="614" y="862" /><part name="64" x="681" y="843" /><part name="65" x="614" y="862" /><part name="66" x="572" y="869" /><part name="67" x="531" y="866" /></box></image><image file="images/robvid_frame659.jpg"><box top="100" left="100" width="880" height="1000"><part name="00" x="239" y="500" /><part name="01" x="241" y="576" /><part name="02" x="260" y="650" /><part name="03" x="281" y="725" /><part name="04" x="308" y="801" /><part name="05" x="349" y="859" /><part name="06" x="396" y="926" /><part name="07" x="466" y="992" /><part name="08" x="550" y="1007" /><part name="09" x="639" y="990" /><part name="10" x="685" y="946" /><part name="11" x="725" y="875" /><part name="12" x="761" y="807" /><part name="13" x="787" y="734" /><part name="14" x="799" y="651" /><part name="15" x="802" y="572" /><part name="16" x="801" y="487" /><part name="17" x="282" y="446" /><part name="18" x="308" y="400" /><part name="19" x="354" y="393" /><part name="20" x="416" y="395" /><part name="21" x="479" y="411" /><part name="22" x="579" y="408" /><part name="23" x="638" y="389" /><part name="24" x="696" y="380" /><part name="25" x="753" y="394" /><part name="26" x="782" y="436" /><part name="27" x="540" y="471" /><part name="28" x="545" y="542" /><part name="29" x="549" y="612" /><part name="30" x="550" y="685" /><part name="31" x="464" y="690" /><part name="32" x="504" y="704" /><part name="33" x="550" y="723" /><part name="34" x="593" y="705" /><part name="35" x="630" y="687" /><part name="36" x="344" y="496" /><part name="37" x="382" y="468" /><part name="38" x="431" y="469" /><part name="39" x="469" y="495" /><part name="40" x="435" y="519" /><part name="41" x="387" y="522" /><part name="42" x="599" y="489" /><part name="43" x="643" y="456" /><part name="44" x="686" y="454" /><part name="45" x="720" y="481" /><part name="46" x="684" y="499" /><part name="47" x="642" y="503" /><part name="48" x="437" y="778" /><part name="49" x="481" y="775" /><part name="50" x="515" y="775" /><part name="51" x="547" y="785" /><part name="52" x="575" y="771" /><part name="53" x="621" y="773" /><part name="54" x="671" y="779" /><part name="55" x="624" y="838" /><part name="56" x="581" y="852" /><part name="57" x="545" y="862" /><part name="58" x="516" y="853" /><part name="59" x="473" y="833" /><part name="60" x="445" y="782" /><part name="61" x="503" y="809" /><part name="62" x="551" y="814" /><part name="63" x="597" y="801" /><part name="64" x="658" y="783" /><part name="65" x="595" y="788" /><part name="66" x="550" y="793" /><part name="67" x="506" y="785" /></box></image><image file="images/robvid_frame639.jpg"><box top="100" left="100" width="880" height="1000"><part name="00" x="238" y="502" /><part name="01" x="241" y="579" /><part name="02" x="261" y="655" /><part name="03" x="287" y="730" /><part name="04" x="318" y="808" /><part name="05" x="358" y="872" /><part name="06" x="408" y="940" /><part name="07" x="478" y="1009" /><part name="08" x="566" y="1026" /><part name="09" x="653" y="1005" /><part name="10" x="696" y="960" /><part name="11" x="729" y="885" /><part name="12" x="769" y="816" /><part name="13" x="793" y="741" /><part name="14" x="803" y="655" /><part name="15" x="805" y="575" /><part name="16" x="803" y="487" /><part name="17" x="280" y="449" /><part name="18" x="308" y="406" /><part name="19" x="353" y="400" /><part name="20" x="414" y="402" /><part name="21" x="477" y="418" /><part name="22" x="572" y="413" /><part name="23" x="630" y="394" /><part name="24" x="689" y="383" /><part name="25" x="744" y="397" /><part name="26" x="782" y="438" /><part name="27" x="539" y="473" /><part name="28" x="543" y="544" /><part name="29" x="547" y="615" /><part name="30" x="549" y="688" /><part name="31" x="463" y="692" /><part name="32" x="503" y="707" /><part name="33" x="549" y="726" /><part name="34" x="592" y="708" /><part name="35" x="629" y="689" /><part name="36" x="343" y="499" /><part name="37" x="383" y="476" /><part name="38" x="431" y="479" /><part name="39" x="468" y="496" /><part name="40" x="433" y="517" /><part name="41" x="387" y="521" /><part name="42" x="599" y="489" /><part name="43" x="642" y="463" /><part name="44" x="686" y="462" /><part name="45" x="720" y="485" /><part name="46" x="681" y="500" /><part name="47" x="644" y="495" /><part name="48" x="436" y="795" /><part name="49" x="481" y="778" /><part name="50" x="515" y="772" /><part name="51" x="548" y="781" /><part name="52" x="583" y="764" /><part name="53" x="623" y="769" /><part name="54" x="670" y="787" /><part name="55" x="625" y="863" /><part name="56" x="581" y="884" /><part name="57" x="544" y="898" /><part name="58" x="510" y="887" /><part name="59" x="469" y="862" /><part name="60" x="449" y="798" /><part name="61" x="498" y="832" /><part name="62" x="554" y="845" /><part name="63" x="600" y="825" /><part name="64" x="632" y="792" /><part name="65" x="597" y="786" /><part name="66" x="549" y="792" /><part name="67" x="497" y="792" /></box></image></images></dataset>